joblet/__init__.py
joblet/_proto_generation_info.py
joblet/client.py
joblet/config.py
joblet/exceptions.py
joblet/helpers.py
joblet/services.py
joblet/types.py
joblet/proto/__init__.py
joblet/proto/joblet_pb2.py
joblet/proto/joblet_pb2.pyi
joblet/proto/joblet_pb2_grpc.py
joblet_sdk_python-2.5.1.dist-info/licenses/LICENSE
joblet_sdk_python-2.5.1.dist-info/METADATA
joblet_sdk_python-2.5.1.dist-info/WHEEL
joblet_sdk_python-2.5.1.dist-info/top_level.txt
joblet_sdk_python-2.5.1.dist-info/RECORD
