Metadata-Version: 2.4
Name: joblet-sdk-python
Version: 2.5.1
Summary: Python SDK for Joblet - A distributed task execution system
Author: Jay Ehsaniara
License-Expression: MIT
Project-URL: Homepage, https://github.com/ehsaniara/joblet-sdk-python
Project-URL: Issues, https://github.com/ehsaniara/joblet-sdk-python/issues
Classifier: Development Status :: 4 - Beta
Classifier: Intended Audience :: Developers
Classifier: Programming Language :: Python :: 3
Classifier: Programming Language :: Python :: 3.9
Classifier: Programming Language :: Python :: 3.10
Classifier: Programming Language :: Python :: 3.11
Classifier: Programming Language :: Python :: 3.12
Requires-Python: >=3.9
License-File: LICENSE
Requires-Dist: grpcio>=1.75.1
Requires-Dist: protobuf>=4.25.0
Requires-Dist: pyyaml>=6.0
Provides-Extra: aws
Requires-Dist: boto3>=1.28.0; extra == "aws"
Provides-Extra: dev
Requires-Dist: grpcio-tools>=1.75.1; extra == "dev"
Requires-Dist: pytest>=7.0; extra == "dev"
Requires-Dist: pytest-cov>=4.0; extra == "dev"
Requires-Dist: pytest-asyncio>=0.21; extra == "dev"
Requires-Dist: pre-commit>=3.0; extra == "dev"
Requires-Dist: mypy>=1.0; extra == "dev"
Requires-Dist: types-pyyaml; extra == "dev"
Requires-Dist: types-protobuf; extra == "dev"
Requires-Dist: boto3>=1.28.0; extra == "dev"
Requires-Dist: moto>=4.0.0; extra == "dev"
Dynamic: license-file
